buttons_and_dials/__init__.py
buttons_and_dials/config_set.py
buttons_and_dials-0.1.5.dist-info/LICENSE
buttons_and_dials-0.1.5.dist-info/METADATA
buttons_and_dials-0.1.5.dist-info/WHEEL
buttons_and_dials-0.1.5.dist-info/RECORD
