Metadata-Version: 2.1
Name: buttons-and-dials
Version: 0.1.5
Summary: 
Author: Javier Mansilla
Author-email: javimansilla@gmail.com
Requires-Python: >=3.10,<4.0
Classifier: Programming Language :: Python :: 3
Classifier: Programming Language :: Python :: 3.10
Classifier: Programming Language :: Python :: 3.11
Classifier: Programming Language :: Python :: 3.12
Requires-Dist: tomli (>=2.2.1,<3.0.0)
